{
  "type": "FeatureCollection",
  "features": [
    {
      "type": "Feature",
      "properties": {
        "cntry_name": "Blue Horde",
        "gwsdate": "1400-01-01T00:00:00",
        "gwsyear": 1400,
        "gwsmonth": 1,
        "gwsday": 1,
        "gwedate": "1492-01-01T00:00:00",
        "gweyear": 1492,
        "gwemonth": 1,
        "gweday": 1
      },
      "geometry": {
        "type": "MultiPolygon",
        "coordinates": [
          [
            [
              [
                47.83201023532538,
                57.81341151790118
              ],
              [
                50.20723437374214,
                46.66025834802806
              ],
              [
                49.9481420845821,
                46.559501253325365
              ],
              [
                49.723345789416086,
                46.532523714262865
              ],
              [
                49.53451446007038,
                46.54151877041521
              ],
              [
                49.40862945030476,
                46.43361624355974
              ],
              [
                49.31320479820515,
                46.352687441069506
              ],
              [
                49.23778441856648,
                46.26276739712419
              ],
              [
                49.05794433067585,
                46.13688238735857
              ],
              [
                48.88709929893757,
                46.082931123930834
              ],
              [
                48.833148035509836,
                46.082931123930834
              ],
              [
                48.833148035509836,
                46.01998861904802
              ],
              [
                48.833148035509836,
                45.92107733364763
              ],
              [
                48.770205530627024,
                45.88510855313005
              ],
              [
                48.63532927940632,
                45.975028597075365
              ],
              [
                48.482466730578196,
                45.88510855313005
              ],
              [
                48.30262664268757,
                45.768214784819506
              ],
              [
                48.01488784263874,
                45.71426352139177
              ],
              [
                47.871016535265696,
                45.67829855557146
              ],
              [
                47.75412276695515,
                45.71426352139177
              ],
              [
                47.67319777916218,
                45.75023230190935
              ],
              [
                47.628237757189524,
                45.73224981899919
              ],
              [
                47.60126403282429,
                45.66031225796404
              ],
              [
                47.65521148155476,
                45.54341848965349
              ],
              [
                47.55630401085163,
                45.45349844570818
              ],
              [
                47.4753752083614,
                45.318622194487475
              ],
              [
                47.39445022056843,
                45.17475088711443
              ],
              [
                47.25057891319538,
                44.98592337246599
              ],
              [
                47.169653925402415,
                44.860038362700365
              ],
              [
                47.02578261802937,
                44.78810080166521
              ],
              [
                46.87292006920124,
                44.68019827480974
              ],
              [
                46.80997756431843,
                44.53633078213396
              ],
              [
                46.84594634483601,
                44.446410738188646
              ],
              [
                46.99880507896687,
                44.356490694243334
              ],
              [
                47.142676386339915,
                44.33850821133318
              ],
              [
                47.22360137413288,
                44.20362814541521
              ],
              [
                47.33150771568562,
                44.18564566250505
              ],
              [
                47.43940642784382,
                44.03278311367693
              ],
              [
                47.56529525230671,
                43.84395559902849
              ],
              [
                47.53831771324421,
                43.67311056729021
              ],
              [
                47.49336150596882,
                43.583190523344896
              ],
              [
                47.520335230334055,
                43.511256777007006
              ],
              [
                47.56529525230671,
                43.60117300625505
              ],
              [
                47.61025527427937,
                43.75403555508318
              ],
              [
                47.6642065377071,
                43.85294684048357
              ],
              [
                47.73614028404499,
                43.861938081938646
              ],
              [
                47.67319777916218,
                43.664115511137865
              ],
              [
                47.57428649376179,
                43.50226172085466
              ],
              [
                47.60126403282429,
                43.3224254476613
              ],
              [
                47.65521148155476,
                43.277465425688646
              ],
              [
                47.58327773521687,
                43.1875491964406
              ],
              [
                47.56529525230671,
                43.007709108549975
              ],
              [
                47.73614028404499,
                42.899806581694506
              ],
              [
                47.79009154747273,
                42.85484655972185
              ],
              [
                47.84404281090046,
                42.621059023100756
              ],
              [
                47.39487912288488,
                42.58778552685864
              ],
              [
                45.8608618111446,
                42.474147402007006
              ],
              [
                45.80767730186726,
                42.53797110195818
              ],
              [
                45.648116144640696,
                42.54860647793474
              ],
              [
                45.47791961143757,
                42.54860647793474
              ],
              [
                45.25983714902755,
                42.43851801493287
              ],
              [
                43.54586158676001,
                42.83470520250434
              ],
              [
                41.12255385826374,
                43.019088350493334
              ],
              [
                40.969336542589915,
                43.076659761626146
              ],
              [
                40.55709365318562,
                43.14658697720232
              ],
              [
                40.25161651085163,
                43.26818426724138
              ],
              [
                40.09806350181843,
                43.37755163784685
              ],
              [
                39.458689722521555,
                43.832931123930834
              ],
              [
                38.92371276329304,
                44.21186026211443
              ],
              [
                38.55609038780476,
                44.385097109038256
              ],
              [
                38.27700332115437,
                44.42320593472185
              ],
              [
                38.10918334434773,
                44.493774019438646
              ],
              [
                37.880373987658274,
                44.71894796963396
              ],
              [
                37.774050745470774,
                44.74454077358904
              ],
              [
                37.62174514244343,
                44.67330893154802
              ],
              [
                37.47389129112507,
                44.69235952969255
              ],
              [
                37.31793883751179,
                44.92420920010271
              ],
              [
                36.95986846397663,
                45.227355562407396
              ],
              [
                37.22774795006062,
                45.31201895352068
              ],
              [
                37.4609709114864,
                45.31247671719255
              ],
              [
                37.661265406115305,
                45.345233522612475
              ],
              [
                37.70609572838093,
                45.57840307827654
              ],
              [
                37.867877039416086,
                45.79251440640154
              ],
              [
                37.98994353721882,
                46.00666006680193
              ],
              [
                38.22715285728718,
                46.02009161587419
              ],
              [
                38.45897963951374,
                46.07891424771013
              ],
              [
                38.2649145455196,
                46.31855734463396
              ],
              [
                37.970171961291086,
                46.441283785063646
              ],
              [
                37.757098230822336,
                46.60319098110857
              ],
              [
                37.8665991158321,
                46.65535696621599
              ],
              [
                38.031863245470774,
                46.66868170376482
              ],
              [
                38.40109160850788,
                46.7213512289113
              ],
              [
                38.72273925255085,
                46.877921663481615
              ],
              [
                39.282359156115305,
                47.07403143521013
              ],
              [
                39.194094690783274,
                47.24295004482927
              ],
              [
                39.159853968127024,
                47.26889380093279
              ],
              [
                38.80024627159382,
                47.22916754360857
              ],
              [
                38.209727320177805,
                47.15045889492693
              ],
              [
                37.85925200889851,
                47.103744112212084
              ],
              [
                37.42214492271687,
                47.07688101406755
              ],
              [
                37.19263366173054,
                46.89442022915544
              ],
              [
                36.86455825279499,
                46.809291444975756
              ],
              [
                36.35396865318562,
                46.77579840298357
              ],
              [
                35.85055831383015,
                46.66439016934099
              ],
              [
                35.624331507189524,
                46.52106054897966
              ],
              [
                35.41610244224812,
                46.494689546782396
              ],
              [
                35.21237472008015,
                46.63714178677263
              ],
              [
                35.04636672447468,
                46.357650362212084
              ],
              [
                34.906809839709055,
                46.27302130337419
              ],
              [
                34.69234755943562,
                46.25312765713396
              ],
              [
                34.49565413902546,
                46.27870138760271
              ],
              [
                34.06421569298054,
                46.26487311001482
              ],
              [
                33.83908370445515,
                46.193053804594896
              ],
              [
                34.12725737999226,
                46.06389959927263
              ],
              [
                35.00805190513874,
                45.61194571133318
              ],
              [
                35.031897577746165,
                45.53427466030779
              ],
              [
                34.9900122017696,
                45.45001562710466
              ],
              [
                35.063418421252024,
                45.34009894009294
              ],
              [
                35.31667617271687,
                45.32118185635271
              ],
              [
                35.54621795128132,
                45.37989386196794
              ],
              [
                35.8497648567989,
                45.4452281820363
              ],
              [
                36.323164972765696,
                45.439696871001146
              ],
              [
                36.52104857872273,
                45.38828619595232
              ],
              [
                36.41513350914265,
                45.271571718413256
              ],
              [
                36.36711409996296,
                45.161483370024584
              ],
              [
                36.264754328234446,
                45.09658774014177
              ],
              [
                36.00469878624226,
                45.04433401699724
              ],
              [
                35.865454706652415,
                45.031119905669115
              ],
              [
                35.59955504844929,
                45.10174139614763
              ],
              [
                35.386660608752024,
                45.08192404385271
              ],
              [
                35.06732085655476,
                44.86172445889177
              ],
              [
                34.61416152427937,
                44.8414684164113
              ],
              [
                34.37224105308796,
                44.75717505093279
              ],
              [
                34.13495543907429,
                44.53749807949724
              ],
              [
                34.01372435997273,
                44.49212225552263
              ],
              [
                33.66015532921101,
                44.52365835781755
              ],
              [
                33.39549544761921,
                44.600490175444506
              ],
              [
                33.55937865684773,
                44.93613775845232
              ],
              [
                33.516673120959055,
                45.12350805874529
              ],
              [
                33.397872004015696,
                45.25268133755388
              ],
              [
                33.013491663439524,
                45.38137014980974
              ],
              [
                32.926287683947336,
                45.38767202969255
              ],
              [
                32.64344695518757,
                45.380633913237475
              ],
              [
                32.575301203234446,
                45.361083589751146
              ],
              [
                32.50324157188679,
                45.44510229702654
              ],
              [
                32.902258905871165,
                45.67258032437029
              ],
              [
                33.19164946983601,
                45.78977545376482
              ],
              [
                33.53945830772663,
                45.874713503081225
              ],
              [
                33.638838800890696,
                45.92677267666521
              ],
              [
                33.52794555137898,
                46.13406332607927
              ],
              [
                33.33253386925007,
                46.16611059780779
              ],
              [
                32.9729338021114,
                46.14594992275896
              ],
              [
                32.51644423912312,
                46.12558325405779
              ],
              [
                32.202166590197336,
                46.17036017056169
              ],
              [
                32.11410430382038,
                46.215621553618334
              ],
              [
                31.925940546496165,
                46.409930788237475
              ],
              [
                32.188792261584055,
                46.59223898525896
              ],
              [
                31.951270136339915,
                46.86462744351091
              ],
              [
                31.78104690025593,
                46.701861940581225
              ],
              [
                31.53773406456257,
                46.701381288725756
              ],
              [
                31.087231668932688,
                46.6355357992238
              ],
              [
                30.832856211169016,
                46.576591097075365
              ],
              [
                30.52046111534382,
                46.25140722866716
              ],
              [
                30.432847403352774,
                46.175749569852435
              ],
              [
                30.380036249832592,
                46.130145198757525
              ],
              [
                29.121199124709765,
                48.20262194156298
              ],
              [
                29.456202042798395,
                48.36469388440768
              ],
              [
                29.84803193240183,
                49.278963626815695
              ],
              [
                34.680600570844234,
                48.56060882920939
              ],
              [
                37.03157990846486,
                49.73609849801971
              ],
              [
                38.1417645956746,
                49.60548853481856
              ],
              [
                38.18090574737083,
                49.996900051780834
              ],
              [
                30.815918893176537,
                56.15044232220778
              ],
              [
                30.93559509207821,
                56.389794720011125
              ],
              [
                30.73811447292015,
                56.98223657748532
              ],
              [
                31.281186175604823,
                57.27845750622241
              ],
              [
                32.416699735763686,
                57.27845750622241
              ],
              [
                32.52553617802532,
                57.899221198091325
              ],
              [
                33.50511090203392,
                57.9645261796919
              ],
              [
                34.28877068124079,
                57.833916216490756
              ],
              [
                36.11731016605684,
                56.72373152928101
              ],
              [
                37.74993470607116,
                56.98495145568331
              ],
              [
                38.860119393280904,
                58.35635606929534
              ],
              [
                38.40298452207689,
                59.27062581170336
              ],
              [
                36.24792012925798,
                60.1195905725108
              ],
              [
                36.31322511085855,
                60.6420304253154
              ],
              [
                37.09688489006543,
                61.16447027811998
              ],
              [
                37.88054466927231,
                61.03386031491883
              ],
              [
                39.8396941172895,
                60.1195905725108
              ],
              [
                40.949878804499235,
                60.18489555411138
              ],
              [
                41.211098730901526,
                60.446115480513676
              ],
              [
                41.211098730901526,
                61.16447027811998
              ],
              [
                45.71714246134106,
                62.20934998372915
              ],
              [
                46.04366736934393,
                62.078740020527995
              ],
              [
                45.96480886560179,
                57.734515685377644
              ],
              [
                47.83201023532538,
                57.81341151790118
              ]
            ]
          ]
        ]
      }
    }
  ]
}