{
  "type": "FeatureCollection",
  "features": [
    {
      "type": "Feature",
      "properties": {
        "cntry_name": "JohnDoe_80",
        "gwsdate": "100-01-01T00:00:00",
        "gwsyear": 100,
        "gwsmonth": 1,
        "gwsday": 1,
        "gwedate": "200-01-01T00:00:00",
        "gweyear": 200,
        "gwemonth": 1,
        "gweday": 1
      },
      "geometry": {
        "type": "MultiPolygon",
        "coordinates": [
          [
            [
              [
                -69.33532425442583,
                -54.29167977718945
              ],
              [
                -69.47352310696489,
                -54.21842233090039
              ],
              [
                -69.7256974844063,
                -54.165455259367185
              ],
              [
                -69.80562302151567,
                -54.12552300839062
              ],
              [
                -69.89021774807817,
                -54.13904611019726
              ],
              [
                -70.04246231594927,
                -53.98573724178906
              ],
              [
                -70.14553543606645,
                -53.80573312191601
              ],
              [
                -70.14553543603759,
                -53.805733121905604
              ],
              [
                -70.04246231605266,
                -53.98573724154768
              ],
              [
                -69.89021774818157,
                -54.139046109955885
              ],
              [
                -69.80562302161907,
                -54.125523008149244
              ],
              [
                -69.7256974845097,
                -54.16545525912581
              ],
              [
                -69.47352310706829,
                -54.21842233065901
              ],
              [
                -69.33532425452923,
                -54.29167977694807
              ],
              [
                -69.05546280433391,
                -54.60197869662581
              ],
              [
                -69.0554628044473,
                -54.601978696626816
              ],
              [
                -69.33532425442583,
                -54.29167977718945
              ]
            ]
          ],
          [
            [
              [
                -69.51457687893755,
                -53.34461251644726
              ],
              [
                -70.33333298245317,
                -53.47274438290234
              ],
              [
                -70.4647111562813,
                -53.373070158048826
              ],
              [
                -70.46471115621767,
                -53.373070157934166
              ],
              [
                -70.33333298255657,
                -53.47274438266096
              ],
              [
                -69.51457687904094,
                -53.344612516205885
              ],
              [
                -69.4406633048222,
                -53.411072171967604
              ],
              [
                -69.4406633047963,
                -53.41107217213929
              ],
              [
                -69.51457687893755,
                -53.34461251644726
              ]
            ]
          ],
          [
            [
              [
                -68.33215042630083,
                -52.85004083065625
              ],
              [
                -68.30537888089067,
                -52.943050779386716
              ],
              [
                -68.46481796780473,
                -53.08300820736523
              ],
              [
                -68.70525833637359,
                -53.23463097952938
              ],
              [
                -68.70525833656048,
                -53.23463097934065
              ],
              [
                -68.46481796790813,
                -53.083008207123854
              ],
              [
                -68.30537888099407,
                -52.94305077914534
              ],
              [
                -68.33215042633857,
                -52.85004083064296
              ],
              [
                -68.33215042630083,
                -52.85004083065625
              ]
            ]
          ],
          [
            [
              [
                -65.2592439321602,
                -54.71877709774609
              ],
              [
                -65.26215836087114,
                -54.81925240902539
              ],
              [
                -65.34770676175005,
                -54.91323510555859
              ],
              [
                -65.56909653225786,
                -54.94046441464062
              ],
              [
                -66.10820480862505,
                -54.98171655087109
              ],
              [
                -66.45801254788286,
                -55.069725431486326
              ],
              [
                -66.62184616604692,
                -55.07004205135937
              ],
              [
                -67.15256210842973,
                -54.90997735409375
              ],
              [
                -67.49159714260942,
                -54.87041512875195
              ],
              [
                -68.00916763821489,
                -54.858013547941404
              ],
              [
                -68.37550064602739,
                -54.85200158505078
              ],
              [
                -68.74939438382036,
                -54.88858453182812
              ],
              [
                -69.21397110501177,
                -54.934017576261716
              ],
              [
                -69.4240388540352,
                -54.88080636410351
              ],
              [
                -69.6717195180977,
                -54.77409402279492
              ],
              [
                -69.86098953762895,
                -54.774456419035154
              ],
              [
                -70.07761093655473,
                -54.82176247982617
              ],
              [
                -70.49821945706255,
                -54.92306558041211
              ],
              [
                -70.72149368801958,
                -54.93690148739453
              ],
              [
                -70.72149368792667,
                -54.936901487140986
              ],
              [
                -70.49821945716594,
                -54.92306558017073
              ],
              [
                -70.07761093665813,
                -54.82176247958479
              ],
              [
                -69.86098953773235,
                -54.774456418793775
              ],
              [
                -69.6717195182011,
                -54.77409402255354
              ],
              [
                -69.4240388541386,
                -54.880806363862135
              ],
              [
                -69.21397110511516,
                -54.93401757602034
              ],
              [
                -68.74939438392376,
                -54.888584531586744
              ],
              [
                -68.37550064613079,
                -54.8520015848094
              ],
              [
                -68.00916763831829,
                -54.858013547700025
              ],
              [
                -67.49159714271282,
                -54.87041512851057
              ],
              [
                -67.15256210853313,
                -54.90997735385237
              ],
              [
                -66.62184616615032,
                -55.070042051117994
              ],
              [
                -66.45801254798626,
                -55.06972543124495
              ],
              [
                -66.10820480872844,
                -54.98171655062971
              ],
              [
                -65.56909653236126,
                -54.940464414399244
              ],
              [
                -65.34770676185344,
                -54.91323510531721
              ],
              [
                -65.26215836097454,
                -54.81925240878401
              ],
              [
                -65.25924393227095,
                -54.718777097757936
              ],
              [
                -65.2592439321602,
                -54.71877709774609
              ]
            ]
          ]
        ]
      }
    }
  ]
}