{
  "type": "FeatureCollection",
  "features": [
    {
      "type": "Feature",
      "properties": {
        "cntry_name": "Kurnai",
        "gwsdate": "1715-01-01T00:00:00",
        "gwsyear": 1715,
        "gwsmonth": 1,
        "gwsday": 1,
        "gwedate": "1783-01-01T00:00:00",
        "gweyear": 1783,
        "gwemonth": 1,
        "gweday": 1
      },
      "geometry": {
        "type": "MultiPolygon",
        "coordinates": [
          [
            [
              [
                146.91714003990435,
                -38.71336404208479
              ],
              [
                146.91427564919013,
                -38.717178416302396
              ],
              [
                146.859741,
                -38.74123
              ],
              [
                146.651,
                -38.76265
              ],
              [
                146.453247,
                -38.749799
              ],
              [
                146.326904,
                -38.749799
              ],
              [
                146.217041,
                -38.728375
              ],
              [
                146.244506,
                -38.625453
              ],
              [
                146.293945,
                -38.440682
              ],
              [
                146.321411,
                -38.32011
              ],
              [
                146.321411,
                -38.216604
              ],
              [
                146.321411,
                -38.130235
              ],
              [
                146.409301,
                -37.974514
              ],
              [
                146.387329,
                -37.83148
              ],
              [
                146.293945,
                -37.657732
              ],
              [
                146.178588,
                -37.522797
              ],
              [
                146.162109,
                -37.426888
              ],
              [
                146.409301,
                -37.339591
              ],
              [
                146.678466,
                -37.225954
              ],
              [
                146.903686,
                -37.077093
              ],
              [
                147.183837,
                -37.002552
              ],
              [
                147.293701,
                -37.103384
              ],
              [
                147.420043,
                -37.291535
              ],
              [
                147.507934,
                -37.4138
              ],
              [
                147.546386,
                -37.483576
              ],
              [
                147.705688,
                -37.405073
              ],
              [
                147.793579,
                -37.348326
              ],
              [
                147.881469,
                -37.278423
              ],
              [
                148.051757,
                -37.169071
              ],
              [
                148.156127,
                -37.160316
              ],
              [
                148.172607,
                -37.225954
              ],
              [
                148.320922,
                -37.326488
              ],
              [
                148.452758,
                -37.409437
              ],
              [
                148.699951,
                -37.474858
              ],
              [
                148.958129,
                -37.479217
              ],
              [
                149.25476,
                -37.618582
              ],
              [
                149.315185,
                -37.735969
              ],
              [
                149.309692,
                -37.83148
              ],
              [
                149.057006,
                -37.86618
              ],
              [
                148.809814,
                -37.861844
              ],
              [
                148.326416,
                -37.900865
              ],
              [
                148.046264,
                -37.95286
              ],
              [
                147.74414,
                -38.052416
              ],
              [
                147.5354,
                -38.212288
              ],
              [
                147.112426,
                -38.561052
              ],
              [
                146.986083,
                -38.685509
              ],
              [
                146.93403392339806,
                -38.7084643639909
              ],
              [
                146.91714003990435,
                -38.71336404208479
              ]
            ]
          ]
        ]
      }
    }
  ]
}