{
  "type": "FeatureCollection",
  "features": [
    {
      "type": "Feature",
      "properties": {
        "cntry_name": "JohnDoe_158",
        "gwsdate": "-5000-01-01T00:00:00",
        "gwsyear": -5000,
        "gwsmonth": 1,
        "gwsday": 1,
        "gwedate": "-4000-01-01T00:00:00",
        "gweyear": -4000,
        "gwemonth": 1,
        "gweday": 1
      },
      "geometry": {
        "type": "MultiPolygon",
        "coordinates": [
          [
            [
              [
                78.495529,
                71.047211
              ],
              [
                78.50000000000011,
                71.041092
              ],
              [
                78.49581485925357,
                71.04050734704357
              ],
              [
                78.49124433436945,
                71.0482357640483
              ],
              [
                78.495529,
                71.047211
              ]
            ]
          ]
        ]
      }
    }
  ]
}