{
  "type": "FeatureCollection",
  "features": [
    {
      "type": "Feature",
      "properties": {
        "cntry_name": "Bagan",
        "gwsdate": "1200-01-01T00:00:00",
        "gwsyear": 1200,
        "gwsmonth": 1,
        "gwsday": 1,
        "gwedate": "1279-01-01T00:00:00",
        "gweyear": 1279,
        "gwemonth": 1,
        "gweday": 1
      },
      "geometry": {
        "type": "MultiPolygon",
        "coordinates": [
          [
            [
              [
                99.4823042303804,
                21.658814194745478
              ],
              [
                97.53177572596498,
                18.882499882063087
              ],
              [
                97.44394394179479,
                19.10207934248855
              ],
              [
                97.00836514269544,
                19.198874631177297
              ],
              [
                96.69927277139944,
                19.124266127761025
              ],
              [
                96.47599105490731,
                21.763949781429105
              ],
              [
                95.89521932277485,
                22.63510737962784
              ],
              [
                95.4596405236755,
                22.731902668316586
              ],
              [
                94.87886879154298,
                22.68350502397221
              ],
              [
                94.29809705941052,
                22.29632386921722
              ],
              [
                93.96558669517783,
                19.194356523711107
              ],
              [
                93.83903792808799,
                18.952691637236498
              ],
              [
                93.69466689537315,
                19.009553514677904
              ],
              [
                93.45794204185752,
                19.174213014799975
              ],
              [
                93.67500594566611,
                19.250913225371264
              ],
              [
                93.81499770592002,
                19.257560335356615
              ],
              [
                93.74783614586143,
                19.47339781399431
              ],
              [
                93.72381881187705,
                19.5940376150197
              ],
              [
                93.41599563072471,
                19.94275816555681
              ],
              [
                93.33432296226768,
                20.025172792632006
              ],
              [
                93.24848464439658,
                20.037692629057787
              ],
              [
                93.06563094566611,
                19.99283369656267
              ],
              [
                92.89442733238486,
                20.113166414458178
              ],
              [
                92.93328383873252,
                20.31016882534685
              ],
              [
                92.92148116539268,
                20.37367209072771
              ],
              [
                92.82709792564658,
                20.424287401396654
              ],
              [
                92.66279128502158,
                20.404885851103685
              ],
              [
                92.40335372398643,
                20.61396177883806
              ],
              [
                92.1762953133419,
                20.886634432036303
              ],
              [
                92.12366774986533,
                20.996430956084154
              ],
              [
                92.06685927818565,
                21.115090929228685
              ],
              [
                91.9460478157833,
                21.36257895107927
              ],
              [
                91.84590438316611,
                21.908670030791185
              ],
              [
                91.5710707039669,
                22.543313585478685
              ],
              [
                91.41017440269736,
                22.72083433743181
              ],
              [
                93.62053003858928,
                24.764603730780287
              ],
              [
                93.62237658744698,
                24.76829682849567
              ],
              [
                93.71576708699841,
                24.95507782759854
              ],
              [
                98.62719392439315,
                25.204185650874027
              ],
              [
                99.42824735991412,
                21.66715449274036
              ],
              [
                99.4823042303804,
                21.658814194745478
              ]
            ]
          ]
        ]
      }
    }
  ]
}