{
  "type": "FeatureCollection",
  "features": [
    {
      "type": "Feature",
      "properties": {
        "cntry_name": "JohnDoe_1404",
        "gwsdate": "1492-01-01T00:00:00",
        "gwsyear": 1492,
        "gwsmonth": 1,
        "gwsday": 1,
        "gwedate": "1500-01-01T00:00:00",
        "gweyear": 1500,
        "gwemonth": 1,
        "gweday": 1
      },
      "geometry": {
        "type": "MultiPolygon",
        "coordinates": [
          [
            [
              [
                -77.00855241229384,
                -2.314218876245147
              ],
              [
                -77.009586,
                -2.313774
              ],
              [
                -77.01096072741169,
                -2.311295425381764
              ],
              [
                -77.00962,
                -2.311439
              ],
              [
                -77.00855241229384,
                -2.314218876245147
              ]
            ]
          ]
        ]
      }
    }
  ]
}