{
  "type": "FeatureCollection",
  "features": [
    {
      "type": "Feature",
      "properties": {
        "cntry_name": "JohnDoe_212",
        "gwsdate": "200-01-01T00:00:00",
        "gwsyear": 200,
        "gwsmonth": 1,
        "gwsday": 1,
        "gwedate": "300-01-01T00:00:00",
        "gweyear": 300,
        "gwemonth": 1,
        "gweday": 1
      },
      "geometry": {
        "type": "MultiPolygon",
        "coordinates": [
          [
            [
              [
                -83.8099866194149,
                43.65294649760638
              ],
              [
                -83.874516475,
                43.68453372499999
              ],
              [
                -84.77309296795586,
                43.382835851404835
              ],
              [
                -84.90267536970708,
                43.523938186140114
              ],
              [
                -85.33461670887786,
                43.99190085257205
              ],
              [
                -86.453372075,
                44.1299426
              ],
              [
                -86.48774414702659,
                44.01941582197994
              ],
              [
                -86.453372075,
                44.1299426
              ],
              [
                -86.329680825,
                44.274861
              ],
              [
                -86.264746725,
                44.433338575
              ],
              [
                -86.258569775,
                44.605375325
              ],
              [
                -86.21421057500001,
                44.70385125
              ],
              [
                -86.13166912499999,
                44.72876635
              ],
              [
                -86.10292376807149,
                44.76138937802109
              ],
              [
                -85.78966652961782,
                44.530551802554314
              ],
              [
                -84.64038790852803,
                45.18679881115734
              ],
              [
                -84.38499265939697,
                45.52330201442785
              ],
              [
                -84.17238032793374,
                45.588873097610495
              ],
              [
                -84.18232252499999,
                45.599460525
              ],
              [
                -84.115050975,
                45.527823175
              ],
              [
                -83.933103275,
                45.45856795
              ],
              [
                -83.636479425,
                45.39169485
              ],
              [
                -83.43090175,
                45.27498137500001
              ],
              [
                -83.31637025,
                45.108427525
              ],
              [
                -83.26047865000001,
                45.02379425
              ],
              [
                -83.26322694999999,
                45.02108155
              ],
              [
                -83.28362185,
                45.025247925
              ],
              [
                -83.32166335,
                45.036293375
              ],
              [
                -83.350038,
                45.050566425
              ],
              [
                -83.3687458,
                45.068067075
              ],
              [
                -83.398025775,
                45.05883305
              ],
              [
                -83.437877925,
                45.02286435
              ],
              [
                -83.421342275,
                44.97439025
              ],
              [
                -83.348418825,
                44.91341075
              ],
              [
                -83.30135795,
                44.840631025
              ],
              [
                -83.28015965,
                44.756051075
              ],
              [
                -83.285912375,
                44.61882965
              ],
              [
                -83.318616125,
                44.42896675
              ],
              [
                -83.3855778,
                44.3126677
              ],
              [
                -83.4867974,
                44.2699325
              ],
              [
                -83.547804975,
                44.19869865
              ],
              [
                -83.568600525,
                44.09896615
              ],
              [
                -83.646453775,
                44.03385505
              ],
              [
                -83.781364725,
                44.00336535
              ],
              [
                -83.8715502,
                43.920205525
              ],
              [
                -83.9170102,
                43.784375575
              ],
              [
                -83.874516475,
                43.684533725
              ],
              [
                -83.744069025,
                43.620679975
              ],
              [
                -83.744069025,
                43.62067997499999
              ],
              [
                -83.8099866194149,
                43.65294649760638
              ]
            ]
          ]
        ]
      }
    }
  ]
}