{
  "type": "FeatureCollection",
  "features": [
    {
      "type": "Feature",
      "properties": {
        "cntry_name": "JohnDoe_340",
        "gwsdate": "-1-01-01T00:00:00",
        "gwsyear": -1,
        "gwsmonth": 1,
        "gwsday": 1,
        "gwedate": "100-01-01T00:00:00",
        "gweyear": 100,
        "gwemonth": 1,
        "gweday": 1
      },
      "geometry": {
        "type": "MultiPolygon",
        "coordinates": [
          [
            [
              [
                86.97762587985152,
                74.29900702090626
              ],
              [
                86.81353286227339,
                74.43529089541798
              ],
              [
                86.81353286227203,
                74.43529089557461
              ],
              [
                86.97762587974812,
                74.29900702114763
              ],
              [
                87.39396956871296,
                74.1794925558156
              ],
              [
                87.54062179039265,
                74.09967383022966
              ],
              [
                87.69079116295124,
                73.90001257534685
              ],
              [
                87.69079116290769,
                73.90001257530088
              ],
              [
                87.54062179049605,
                74.09967382998829
              ],
              [
                87.39396956881636,
                74.17949255557423
              ],
              [
                86.97762587985152,
                74.29900702090626
              ]
            ]
          ]
        ]
      }
    }
  ]
}